{
  "log_id": 2107960391422003912,
  "results": [
    {
      "location": {
        "height": 24,
        "left": 42,
        "top": 32,
        "width": 23
      },
      "name": "kong",
      "score": 1.0
    },
    {
      "location": {
        "height": 23,
        "left": 68,
        "top": 33,
        "width": 23
      },
      "name": "kong",
      "score": 1.0
    },
    {
      "location": {
        "height": 23,
        "left": 67,
        "top": 58,
        "width": 24
      },
      "name": "kong",
      "score": 1.0
    },
    {
      "location": {
        "height": 23,
        "left": 67,
        "top": 83,
        "width": 24
      },
      "name": "kong",
      "score": 1.0
    },
    {
      "location": {
        "height": 23,
        "left": 42,
        "top": 108,
        "width": 23
      },
      "name": "kong",
      "score": 1.0
    },
    {
      "location": {
        "height": 22,
        "left": 67,
        "top": 109,
        "width": 23
      },
      "name": "kong",
      "score": 1.0
    },
    {
      "location": {
        "height": 23,
        "left": 93,
        "top": 108,
        "width": 23
      },
      "name": "kong",
      "score": 1.0
    },
    {
      "location": {
        "height": 23,
        "left": 118,
        "top": 108,
        "width": 23
      },
      "name": "kong",
      "score": 1.0
    },
    {
      "location": {
        "height": 23,
        "left": 192,
        "top": 108,
        "width": 24
      },
      "name": "kong",
      "score": 1.0
    },
    {
      "location": {
        "height": 23,
        "left": 92,
        "top": 184,
        "width": 23
      },
      "name": "kong",
      "score": 1.0
    },
    {
      "location": {
        "height": 24,
        "left": 118,
        "top": 183,
        "width": 23
      },
      "name": "kong",
      "score": 1.0
    },
    {
      "location": {
        "height": 23,
        "left": 143,
        "top": 184,
        "width": 22
      },
      "name": "kong",
      "score": 1.0
    },
    {
      "location": {
        "height": 22,
        "left": 193,
        "top": 184,
        "width": 23
      },
      "name": "kong",
      "score": 1.0
    },
    {
      "location": {
        "height": 23,
        "left": 167,
        "top": 209,
        "width": 23
      },
      "name": "kong",
      "score": 1.0
    },
    {
      "location": {
        "height": 24,
        "left": 142,
        "top": 83,
        "width": 24
      },
      "name": "kong",
      "score": 0.9999998807907104
    },
    {
      "location": {
        "height": 24,
        "left": 118,
        "top": 158,
        "width": 23
      },
      "name": "kong",
      "score": 0.9999998807907104
    },
    {
      "location": {
        "height": 24,
        "left": 193,
        "top": 158,
        "width": 23
      },
      "name": "kong",
      "score": 0.9999998807907104
    },
    {
      "location": {
        "height": 24,
        "left": 168,
        "top": 183,
        "width": 22
      },
      "name": "kong",
      "score": 0.9999998807907104
    },
    {
      "location": {
        "height": 24,
        "left": 167,
        "top": 83,
        "width": 24
      },
      "name": "kong",
      "score": 0.9999997615814209
    },
    {
      "location": {
        "height": 23,
        "left": 67,
        "top": 158,
        "width": 23
      },
      "name": "kong",
      "score": 0.9999997615814209
    },
    {
      "location": {
        "height": 23,
        "left": 192,
        "top": 208,
        "width": 24
      },
      "name": "kong",
      "score": 0.9999997615814209
    },
    {
      "location": {
        "height": 24,
        "left": 168,
        "top": 158,
        "width": 22
      },
      "name": "kong",
      "score": 0.9999996423721313
    },
    {
      "location": {
        "height": 23,
        "left": 17,
        "top": 158,
        "width": 24
      },
      "name": "kong",
      "score": 0.9999995231628418
    },
    {
      "location": {
        "height": 23,
        "left": 43,
        "top": 158,
        "width": 22
      },
      "name": "kong",
      "score": 0.9999995231628418
    },
    {
      "location": {
        "height": 23,
        "left": 18,
        "top": 208,
        "width": 23
      },
      "name": "kong",
      "score": 0.9999995231628418
    },
    {
      "location": {
        "height": 24,
        "left": 17,
        "top": 183,
        "width": 25
      },
      "name": "kong",
      "score": 0.9999994039535522
    },
    {
      "location": {
        "height": 23,
        "left": 143,
        "top": 159,
        "width": 22
      },
      "name": "kong",
      "score": 0.9999991655349731
    },
    {
      "location": {
        "height": 23,
        "left": 93,
        "top": 159,
        "width": 23
      },
      "name": "kong",
      "score": 0.9999984502792358
    },
    {
      "location": {
        "height": 23,
        "left": 167,
        "top": 233,
        "width": 23
      },
      "name": "kong",
      "score": 0.9999825954437256
    },
    {
      "location": {
        "height": 23,
        "left": 192,
        "top": 233,
        "width": 23
      },
      "name": "kong",
      "score": 0.9999817609786987
    },
    {
      "location": {
        "height": 23,
        "left": 78,
        "top": 220,
        "width": 26
      },
      "name": "heizu",
      "score": 0.9959731698036194
    },
    {
      "location": {
        "height": 22,
        "left": 103,
        "top": 46,
        "width": 24
      },
      "name": "heishi",
      "score": 0.9955213069915771
    },
    {
      "location": {
        "height": 24,
        "left": 128,
        "top": 219,
        "width": 25
      },
      "name": "heizu",
      "score": 0.9940096139907837
    },
    {
      "location": {
        "height": 23,
        "left": 129,
        "top": 45,
        "width": 23
      },
      "name": "hongbing",
      "score": 0.9936341047286987
    },
    {
      "location": {
        "height": 23,
        "left": 105,
        "top": 245,
        "width": 23
      },
      "name": "hongshuai",
      "score": 0.992362380027771
    },
    {
      "location": {
        "height": 24,
        "left": 4,
        "top": 244,
        "width": 24
      },
      "name": "heipao",
      "score": 0.9904965162277222
    },
    {
      "location": {
        "height": 24,
        "left": 30,
        "top": 70,
        "width": 22
      },
      "name": "hongche",
      "score": 0.9873298406600952
    },
    {
      "location": {
        "height": 229,
        "left": 15,
        "top": 33,
        "width": 200
      },
      "name": "qipan",
      "score": 0.983367919921875
    },
    {
      "location": {
        "height": 24,
        "left": 153,
        "top": 119,
        "width": 24
      },
      "name": "heixiang",
      "score": 0.9832027554512024
    },
    {
      "location": {
        "height": 25,
        "left": 3,
        "top": 19,
        "width": 25
      },
      "name": "hongpao",
      "score": 0.982208788394928
    },
    {
      "location": {
        "height": 23,
        "left": 204,
        "top": 70,
        "width": 23
      },
      "name": "heixiang",
      "score": 0.9818739891052246
    },
    {
      "location": {
        "height": 25,
        "left": 128,
        "top": 18,
        "width": 24
      },
      "name": "heishi",
      "score": 0.980941653251648
    },
    {
      "location": {
        "height": 24,
        "left": 3,
        "top": 95,
        "width": 25
      },
      "name": "heizu",
      "score": 0.9806445240974426
    },
    {
      "location": {
        "height": 24,
        "left": 103,
        "top": 18,
        "width": 23
      },
      "name": "heijiang",
      "score": 0.9772916436195374
    },
    {
      "location": {
        "height": 23,
        "left": 104,
        "top": 71,
        "width": 23
      },
      "name": "heipao",
      "score": 0.9742079973220825
    },
    {
      "location": {
        "height": 24,
        "left": 54,
        "top": 195,
        "width": 23
      },
      "name": "hongpao",
      "score": 0.9740325808525085
    },
    {
      "location": {
        "height": 24,
        "left": 3,
        "top": 69,
        "width": 25
      },
      "name": "heima",
      "score": 0.9684906601905823
    },
    {
      "location": {
        "height": 23,
        "left": 54,
        "top": 245,
        "width": 22
      },
      "name": "heiche",
      "score": 0.964364230632782
    },
    {
      "location": {
        "height": 24,
        "left": 178,
        "top": 45,
        "width": 25
      },
      "name": "heiche",
      "score": 0.9517970681190491
    }
  ]
}
